k_means_constrained/__init__.py
k_means_constrained/k_means_constrained_.py
k_means_constrained/sklearn_import/__init__.py
k_means_constrained/sklearn_import/base.py
k_means_constrained/sklearn_import/exceptions.py
k_means_constrained/sklearn_import/fixes.py
k_means_constrained/sklearn_import/funcsigs.py
k_means_constrained/sklearn_import/cluster/__init__.py
k_means_constrained/sklearn_import/cluster/_k_means.cp311-win_amd64.pyd
k_means_constrained/sklearn_import/cluster/k_means_.py
k_means_constrained/sklearn_import/externals/__init__.py
k_means_constrained/sklearn_import/externals/funcsigs.py
k_means_constrained/sklearn_import/metrics/__init__.py
k_means_constrained/sklearn_import/metrics/pairwise.py
k_means_constrained/sklearn_import/metrics/pairwise_fast.cp311-win_amd64.pyd
k_means_constrained/sklearn_import/preprocessing/__init__.py
k_means_constrained/sklearn_import/preprocessing/data.py
k_means_constrained/sklearn_import/utils/__init__.py
k_means_constrained/sklearn_import/utils/extmath.py
k_means_constrained/sklearn_import/utils/fixes.py
k_means_constrained/sklearn_import/utils/sparsefuncs.py
k_means_constrained/sklearn_import/utils/sparsefuncs_fast.cp311-win_amd64.pyd
k_means_constrained/sklearn_import/utils/validation.py
k_means_constrained-0.7.6.dist-info/licenses/LICENSE
k_means_constrained-0.7.6.dist-info/METADATA
k_means_constrained-0.7.6.dist-info/WHEEL
k_means_constrained-0.7.6.dist-info/top_level.txt
k_means_constrained-0.7.6.dist-info/RECORD
