Metadata-Version: 2.4
Name: k-means-constrained
Version: 0.7.6
Summary: K-Means clustering constrained with minimum and maximum cluster size
Home-page: https://github.com/joshlk/k-means-constrained
Author: Josh Levy-Kramer
License: BSD 3-Clause
Project-URL: Documentation, https://joshlk.github.io/k-means-constrained/
Project-URL: Code, https://github.com/joshlk/k-means-constrained
Project-URL: Issue tracker, https://github.com/joshlk/k-means-constrained/issues
Classifier: Development Status :: 5 - Production/Stable
Classifier: Intended Audience :: Developers
Classifier: Topic :: Scientific/Engineering
Classifier: License :: OSI Approved :: BSD License
Classifier: Programming Language :: Python :: 3
License-File: LICENSE
Requires-Dist: ortools>=9.11.4210
Requires-Dist: scipy>=1.14.1
Requires-Dist: numpy>=2.1.1
Requires-Dist: six
Requires-Dist: joblib
Dynamic: license-file
Dynamic: requires-dist
